Workbook

Sheet Assumptions
A1: Phillip Morris International - DCF | E1: March 23rd, 2026
E2: *All figures are in USD Millions
A3: Shares Outstanding | B3: 1550 | C3: millions
A4: Current Share price | B4: 166.01 | C4: USD
A5: Net Debt | B5: 43963 | C5: million
A7: Assumptions
A9: Net Revenue Growth Y1 - Y3 | B9: 0.07
A10: Net Revenue Growth Y4-Y7 | B10: 0.05
A11: Terminal Value Growth Y7 onward | B11: 0.02
A13: EBIT Margin | B13: 0.367
A14: D&A as a % of revenue | B14: 0.0491
A15: Capex % of revenue | B15: 0.039
A16: Change in NWC% | B16: 0.005
A17: Tax Rate | B17: 0.197
A19: WACC | B19: 0.0595
A20: Cost of equity | B20: 0.0659
A21: Cost of debt | B21: 0.033
A22: After Tax cost of Debt | B22: 0.0264

Sheet Income Statement
A1: Income Statement
B3: FY2025 | C3: 2026 | D3: 2027 | E3: 2028 | F3: 2029 | G3: 2030 | H3: 2031 | I3: 2032
A4: Base Revenue | B4: 40648
A5: Revenue | C5: =B4*(1+C6) -> 43493.36 | D5: =C5*(1+D6) -> 46537.895 | E5: =D5*(1+E6) -> 49795.548 | F5: =E5*(1+F6) -> 52285.325 | G5: =F5*(1+G6) -> 54899.592 | H5: =G5*(1+H6) -> 57644.571 | I5: =H5*(1+I6) -> 60526.8
A6: Revenue Growth % | C6: =Assumptions!$B$9 -> 0.07 | D6: =Assumptions!$B$9 -> 0.07 | E6: =Assumptions!$B$9 -> 0.07 | F6: =Assumptions!$B$10 -> 0.05 | G6: =Assumptions!$B$10 -> 0.05 | H6: =Assumptions!$B$10 -> 0.05 | I6: =Assumptions!$B$10 -> 0.05
A7: EBIT | C7: =C5*Assumptions!$B$13 -> 15962.063 | D7: =D5*Assumptions!$B$13 -> 17079.408 | E7: =E5*Assumptions!$B$13 -> 18274.966 | F7: =F5*Assumptions!$B$13 -> 19188.714 | G7: =G5*Assumptions!$B$13 -> 20148.15 | H7: =H5*Assumptions!$B$13 -> 21155.558 | I7: =I5*Assumptions!$B$13 -> 22213.335
A8: EBIT Margin % | C8: =Assumptions!$B$13 -> 0.367 | D8: =Assumptions!$B$13 -> 0.367 | E8: =Assumptions!$B$13 -> 0.367 | F8: =Assumptions!$B$13 -> 0.367 | G8: =Assumptions!$B$13 -> 0.367 | H8: =Assumptions!$B$13 -> 0.367 | I8: =Assumptions!$B$13 -> 0.367
A9: Tax | C9: =Assumptions!$B$17*C7 -> 3144.5264 | D9: =Assumptions!$B$17*D7 -> 3364.6433 | E9: =Assumptions!$B$17*E7 -> 3600.1683 | F9: =Assumptions!$B$17*F7 -> 3780.1767 | G9: =Assumptions!$B$17*G7 -> 3969.1856 | H9: =Assumptions!$B$17*H7 -> 4167.6448 | I9: =Assumptions!$B$17*I7 -> 4376.0271
A10: NOPAT | C10: =C7-C9 -> 12817.537 | D10: =D7-D9 -> 13714.764 | E10: =E7-E9 -> 14674.798 | F10: =F7-F9 -> 15408.538 | G10: =G7-G9 -> 16178.965 | H10: =H7-H9 -> 16987.913 | I10: =I7-I9 -> 17837.308

Sheet FCF
A1: FCF
B3: FY2025 | C3: 2026 | D3: 2027 | E3: 2028 | F3: 2029 | G3: 2030 | H3: 2031 | I3: 2032
A4: NOPAT | C4: ='Income Statement'!C10 -> 12817.537 | D4: ='Income Statement'!D10 -> 13714.764 | E4: ='Income Statement'!E10 -> 14674.798 | F4: ='Income Statement'!F10 -> 15408.538 | G4: ='Income Statement'!G10 -> 16178.965 | H4: ='Income Statement'!H10 -> 16987.913 | I4: ='Income Statement'!I10 -> 17837.308
A5: D&A | C5: =Assumptions!$B$14*'Income Statement'!C5 -> 2135.524 | D5: =Assumptions!$B$14*'Income Statement'!D5 -> 2285.0107 | E5: =Assumptions!$B$14*'Income Statement'!E5 -> 2444.9614 | F5: =Assumptions!$B$14*'Income Statement'!F5 -> 2567.2095 | G5: =Assumptions!$B$14*'Income Statement'!G5 -> 2695.5699 | H5: =Assumptions!$B$14*'Income Statement'!H5 -> 2830.3484 | I5: =Assumptions!$B$14*'Income Statement'!I5 -> 2971.8659
A6: CapEx | C6: =Assumptions!$B$15*'Income Statement'!C5 -> 1696.241 | D6: =Assumptions!$B$15*'Income Statement'!D5 -> 1814.9779 | E6: =Assumptions!$B$15*'Income Statement'!E5 -> 1942.0264 | F6: =Assumptions!$B$15*'Income Statement'!F5 -> 2039.1277 | G6: =Assumptions!$B$15*'Income Statement'!G5 -> 2141.0841 | H6: =Assumptions!$B$15*'Income Statement'!H5 -> 2248.1383 | I6: =Assumptions!$B$15*'Income Statement'!I5 -> 2360.5452
A7: Change in NWC | C7: ='Income Statement'!C5*Assumptions!$B$16 -> 217.4668 | D7: ='Income Statement'!D5*Assumptions!$B$16 -> 232.68948 | E7: ='Income Statement'!E5*Assumptions!$B$16 -> 248.97774 | F7: ='Income Statement'!F5*Assumptions!$B$16 -> 261.42663 | G7: ='Income Statement'!G5*Assumptions!$B$16 -> 274.49796 | H7: ='Income Statement'!H5*Assumptions!$B$16 -> 288.22286 | I7: ='Income Statement'!I5*Assumptions!$B$16 -> 302.634
A8: Free Cash Flows | C8: =C4+C5-C6-C7 -> 13039.353 | D8: =D4+D5-D6-D7 -> 13952.108 | E8: =E4+E5-E6-E7 -> 14928.755 | F8: =F4+F5-F6-F7 -> 15675.193 | G8: =G4+G5-G6-G7 -> 16458.952 | H8: =H4+H5-H6-H7 -> 17281.9 | I8: =I4+I5-I6-I7 -> 18145.995

Sheet DCF
A1: DCF
B3: FY2025 | C3: 2026 | D3: 2027 | E3: 2028 | F3: 2029 | G3: 2030 | H3: 2031 | I3: 2032
A4: Free Cash Flows | C4: =FCF!C8 -> 13039.353 | D4: =FCF!D8 -> 13952.108 | E4: =FCF!E8 -> 14928.755 | F4: =FCF!F8 -> 15675.193 | G4: =FCF!G8 -> 16458.952 | H4: =FCF!H8 -> 17281.9 | I4: =FCF!I8 -> 18145.995
A5: Discount Rate | C5: =1/(1+Assumptions!$B$19)^(C3-2025) -> 0.94384143 | D5: =1/(1+Assumptions!$B$19)^(D3-2025) -> 0.89083665 | E5: =1/(1+Assumptions!$B$19)^(E3-2025) -> 0.84080855 | F5: =1/(1+Assumptions!$B$19)^(F3-2025) -> 0.79358994 | G5: =1/(1+Assumptions!$B$19)^(G3-2025) -> 0.74902307 | H5: =1/(1+Assumptions!$B$19)^(H3-2025) -> 0.70695901 | I5: =1/(1+Assumptions!$B$19)^(I3-2025) -> 0.66725721
A6: PV of FCF | C6: =C4*C5 -> 12307.081 | D6: =D4*D5 -> 12429.049 | E6: =E4*E5 -> 12552.225 | F6: =F4*F5 -> 12439.675 | G6: =G4*G5 -> 12328.135 | H6: =H4*H5 -> 12217.595 | I6: =I4*I5 -> 12108.046
A8: Terminal Value | I8: =(I4*(1+Assumptions!$B$11)/(Assumptions!$B$19-Assumptions!$B$11)) -> 468580.13
A9: PV of Terminal Value | I9: =I8*I5 -> 312663.47
A11: Sum of PV of FCF | C11: =SUM(C6:I6) -> 86381.806
A12: PV of Terminal Value | C12: =I9 -> 312663.47
A13: Enterprise Value | C13: =C11+C12 -> 399045.27
A14: Less: Net Debt | C14: =Assumptions!B5 -> 43963
A15: Equity Value | C15: =C13-C14 -> 355082.27
A16: Shares Outstanding | C16: =Assumptions!B3 -> 1550
A17: Implied Share Price | C17: =C15/C16 -> 229.08534

Sheet Sensitivity Analysis
A1: TGR WACC | B1: 0.01 | C1: 0.015 | D1: 0.02 | E1: 0.025 | F1: 0.03 | I1: Current Price
A2: 0.05 | B2: =(DCF!$C$11+(FCF!$I$8*(1+B$1)/($A2-B$1)*DCF!$I$5)-Assumptions!$B$5)/Assumptions!$B$3 -> 224.61095 | C2: =(DCF!$C$11+(FCF!$I$8*(1+C$1)/($A2-C$1)*DCF!$I$5)-Assumptions!$B$5)/Assumptions!$B$3 -> 253.90461 | D2: =(DCF!$C$11+(FCF!$I$8*(1+D$1)/($A2-D$1)*DCF!$I$5)-Assumptions!$B$5)/Assumptions!$B$3 -> 292.96282 | E2: =(DCF!$C$11+(FCF!$I$8*(1+E$1)/($A2-E$1)*DCF!$I$5)-Assumptions!$B$5)/Assumptions!$B$3 -> 347.64432 | F2: =(DCF!$C$11+(FCF!$I$8*(1+F$1)/($A2-F$1)*DCF!$I$5)-Assumptions!$B$5)/Assumptions!$B$3 -> 429.66656 | I2: 46104
A3: 0.055 | B3: =(DCF!$C$11+(FCF!$I$8*(1+B$1)/($A3-B$1)*DCF!$I$5)-Assumptions!$B$5)/Assumptions!$B$3 -> 202.69495 | C3: =(DCF!$C$11+(FCF!$I$8*(1+C$1)/($A3-C$1)*DCF!$I$5)-Assumptions!$B$5)/Assumptions!$B$3 -> 225.5874 | D3: =(DCF!$C$11+(FCF!$I$8*(1+D$1)/($A3-D$1)*DCF!$I$5)-Assumptions!$B$5)/Assumptions!$B$3 -> 255.02056 | E3: =(DCF!$C$11+(FCF!$I$8*(1+E$1)/($A3-E$1)*DCF!$I$5)-Assumptions!$B$5)/Assumptions!$B$3 -> 294.26476 | F3: =(DCF!$C$11+(FCF!$I$8*(1+F$1)/($A3-F$1)*DCF!$I$5)-Assumptions!$B$5)/Assumptions!$B$3 -> 349.20665 | I3: 166.01 | J3: USD
A4: 0.06 | B4: =(DCF!$C$11+(FCF!$I$8*(1+B$1)/($A4-B$1)*DCF!$I$5)-Assumptions!$B$5)/Assumptions!$B$3 -> 185.16215 | C4: =(DCF!$C$11+(FCF!$I$8*(1+C$1)/($A4-C$1)*DCF!$I$5)-Assumptions!$B$5)/Assumptions!$B$3 -> 203.56291 | D4: =(DCF!$C$11+(FCF!$I$8*(1+D$1)/($A4-D$1)*DCF!$I$5)-Assumptions!$B$5)/Assumptions!$B$3 -> 226.56386 | E4: =(DCF!$C$11+(FCF!$I$8*(1+E$1)/($A4-E$1)*DCF!$I$5)-Assumptions!$B$5)/Assumptions!$B$3 -> 256.1365 | F4: =(DCF!$C$11+(FCF!$I$8*(1+F$1)/($A4-F$1)*DCF!$I$5)-Assumptions!$B$5)/Assumptions!$B$3 -> 295.5667
A5: 0.065 | B5: =(DCF!$C$11+(FCF!$I$8*(1+B$1)/($A5-B$1)*DCF!$I$5)-Assumptions!$B$5)/Assumptions!$B$3 -> 170.81714 | C5: =(DCF!$C$11+(FCF!$I$8*(1+C$1)/($A5-C$1)*DCF!$I$5)-Assumptions!$B$5)/Assumptions!$B$3 -> 185.94332 | D5: =(DCF!$C$11+(FCF!$I$8*(1+D$1)/($A5-D$1)*DCF!$I$5)-Assumptions!$B$5)/Assumptions!$B$3 -> 204.43087 | E5: =(DCF!$C$11+(FCF!$I$8*(1+E$1)/($A5-E$1)*DCF!$I$5)-Assumptions!$B$5)/Assumptions!$B$3 -> 227.54031 | F5: =(DCF!$C$11+(FCF!$I$8*(1+F$1)/($A5-F$1)*DCF!$I$5)-Assumptions!$B$5)/Assumptions!$B$3 -> 257.25245
A6: 0.07 | B6: =(DCF!$C$11+(FCF!$I$8*(1+B$1)/($A6-B$1)*DCF!$I$5)-Assumptions!$B$5)/Assumptions!$B$3 -> 158.86295 | C6: =(DCF!$C$11+(FCF!$I$8*(1+C$1)/($A6-C$1)*DCF!$I$5)-Assumptions!$B$5)/Assumptions!$B$3 -> 171.52728 | D6: =(DCF!$C$11+(FCF!$I$8*(1+D$1)/($A6-D$1)*DCF!$I$5)-Assumptions!$B$5)/Assumptions!$B$3 -> 186.72448 | E6: =(DCF!$C$11+(FCF!$I$8*(1+E$1)/($A6-E$1)*DCF!$I$5)-Assumptions!$B$5)/Assumptions!$B$3 -> 205.29883 | F6: =(DCF!$C$11+(FCF!$I$8*(1+F$1)/($A6-F$1)*DCF!$I$5)-Assumptions!$B$5)/Assumptions!$B$3 -> 228.51677

Sheet Qualitative Analysis
A2: PHILIP MORRIS INTERNATIONAL | QUALITATIVE ANALYSIS
A4: Supporting analysis for DCF valuation | March 2026
A6: ▪ BUSINESS OVERVIEW
A7: Philip Morris International (NYSE: PM) is a leading international tobacco and nicotine company, operating in over 180 markets. The company is executing a transformation from combustible cigarettes toward smoke-free products, led by its IQOS heated tobacco platform and ZYN nicotine pouches (via Swedish Match). As of 2025, approximately 40% of PM's net revenues are derived from smoke-free products, with a stated goal of becoming a predominantly smoke-free company by 2030.
A9: ▲ BULL CASE — Supports Assumptions | E9: ▼ BEAR CASE — Key Risks
A10: IQOS Growth Momentum | B10: IQOS has achieved dominant heated tobacco market share in Japan and key European markets. FDA MRTP authorization in the US provides a regulatory tailwind and competitive moat that peers lack. | E10: Combustible Volume Decline | F10: Industry cigarette volumes are declining at 3–5% per annum structurally. If IQOS uptake does not fully offset this, total volumes compress — a key assumption risk in any revenue growth model.
A11: Exceptional Pricing Power | B11: PM has consistently raised combustible prices above inflation for decades. Smoke-free products carry higher ASPs, supporting margin expansion even as volumes shift. | E11: Regulatory Escalation | F11: Governments in Australia, the UK, and the EU have signaled stricter controls on heated tobacco and flavored nicotine products. A broad regulatory crackdown could impair both combustible and IQOS revenues.
A12: ZYN / Nicotine Pouch Optionality | B12: ZYN is the #1 nicotine pouch brand in the US by volume. The category is growing rapidly with minimal regulatory friction, providing a high-margin revenue layer not fully captured in consensus estimates. | E12: FX Headwinds | F12: PM generates ~100% of revenues outside the US. A sustained strong USD environment directly reduces reported revenues and earnings, creating meaningful earnings volatility not captured in local-currency growth rates.
A13: Capital Returns Discipline | B13: PM has maintained and grown its dividend through multiple macro cycles. Share buybacks provide EPS accretion even in flat revenue environments, supporting shareholder value. | E13: Competitive Pressure | F13: BAT (Vuse/glo), Japan Tobacco (Ploom), and KT&G are investing aggressively in heated tobacco. IQOS market share leadership is not guaranteed, particularly in newer geographies.
A14: Emerging Market Penetration | B14: IQOS is in early innings across Southeast Asia, Middle East, and Latin America — large addressable markets with growing middle-class consumers and lower regulatory intensity than Europe. | E14: Swedish Match Integration Risk | F14: The $16B acquisition of Swedish Match in 2022 added significant leverage. Integration execution, ZYN regulatory risk (FDA PMTA), and debt servicing constrain financial flexibility.
A16: ▪ COMPETITIVE POSITIONING & INDUSTRY DYNAMICS
A17: Market Structure | B17: The global tobacco industry is a consolidated oligopoly. PM, BAT, JT, and Altria collectively control ~70% of international volume. High barriers to entry (brand, distribution, regulation) protect incumbents from new entrants.
A18: Smoke-Free Leadership | B18: PM is widely regarded as the most advanced tobacco company in smoke-free transition. IQOS has ~25M users globally (as of 2025), a figure that took peers years to achieve with their own platforms.
A19: ESG & Investor Base | B19: ESG-driven divestment from tobacco continues to narrow PM's institutional investor base and pressures cost of capital over time. However, PM's transformation narrative has attracted some ESG-positive capital back.
A20: Illicit Trade Risk | B20: In high-tax markets (e.g., UK, Australia, parts of MENA), illicit cigarette trade can displace 10–20% of legal volume, constraining PM's ability to raise prices or maintain volume share.
A22: ▪ ASSUMPTION JUSTIFICATION — Linking Qualitative View to DCF Inputs
A23: Assumption | B23: Value Used | C23: Rationale
A24: Revenue Growth Y1-Y3 | B24: 7.0% | C24: Supported by IQOS volume ramp, ZYN expansion, and pricing. Consistent with mid-point of analyst consensus. Risk: combustible volume decline accelerates.
A25: Revenue Growth Y4-Y7 | B25: 5.0% | C25: Step-down reflects maturing IQOS penetration in developed markets and gradual combustible headwinds. Conservative vs. PM's own mid-term guidance.
A26: Terminal Growth Rate | B26: 2.0% | C26: Set at long-run nominal GDP growth. Arguably generous for tobacco — a 1.0–1.5% TGR would be more conservative. Sensitivity table captures this range.
A27: EBIT Margin | B27: 36.7% | C27: Held constant at FY2025 levels. Does not capture smoke-free margin expansion. A 37–39% exit margin by Y7 is plausible if IQOS mix shift continues as expected.
A28: WACC | B28: 5.95% | C28: Reflects PM's investment-grade profile and low beta (~0.7x). Appropriate given stable cash flows but arguably low given leverage (Net Debt/EBITDA ~3.5x post-Swedish Match).
A29: Tax Rate | B29: 19.7% | C29: Based on effective rate from recent filings. Geographically diversified tax base. Risk: OECD 15% global minimum tax implementation could modestly increase rate.
A31: ▪ INVESTMENT CONCLUSION
A32: Our base-case DCF implies an intrinsic value of ~$229/share, representing approximately 38% upside to the current price of $166. This is supported by PM's leading position in smoke-free nicotine, durable pricing power, and above-average FCF conversion. The key risk to the thesis is execution: if IQOS market share gains plateau or combustible volumes decline faster than expected, revenue growth assumptions will prove too optimistic. The terminal value represents ~78% of enterprise value, making the model highly sensitive to the TGR and WACC — both of which are at the generous end of a reasonable range for a tobacco company. On balance, PM appears undervalued at current levels for an investor with a 3–5 year horizon and tolerance for tobacco sector risk. A margin of safety exists even under conservative assumptions (see Sensitivity Analysis sheet).

Sheet Comparable Companies
B2: Philip Morris International — Comparable Company Analysis
B3: As of March 2026 | Figures in USD millions | Source: Public filings, Bloomberg
B5: Trading Comparables
B6: Company | C6: Ticker | D6: Market Cap ($mm) | E6: Enterprise Value ($mm) | F6: EV / EBITDA | G6: P / E (TTM) | H6: EV / Revenue | I6: Div. Yield
B7: Philip Morris | C7: PM | D7: 257000 | E7: 300000 | F7: 17.2 | G7: 22.4 | H7: 7.4 | I7: 0.036
B8: British American Tobacco | C8: BTI | D8: 68000 | E8: 105000 | F8: 7.8 | G8: 11.2 | H8: 4.1 | I8: 0.055
B9: Altria Group | C9: MO | D9: 98000 | E9: 115000 | F9: 9.5 | G9: 11.5 | H9: 5.7 | I9: 0.061
B10: Japan Tobacco | C10: JAPAY | D10: 52000 | E10: 62000 | F10: 8.4 | G10: 17.1 | H10: 2.3 | I10: 0.041
B11: Imperial Brands | C11: IMBBY | D11: 24000 | E11: 38000 | F11: 6.5 | G11: 8.7 | H11: 0.7 | I11: 0.052
B12: Peer Mean | F12: 8.1 | G12: 12.1 | H12: 3.2
B13: Peer Median | F13: 8.1 | G13: 11.3 | H13: 3.2
B15: Valuation Bridge — Implied Share Price vs. DCF
B16: Metric | C16: PM Metric | E16: Peer Median Multiple | G16: Implied EV ($mm) | H16: Implied Price | I16: vs. DCF ($229)
B17: EV / EBITDA | C17: EBITDA: $17,894mm | E17: 8.1x | G17: 144941 | H17: 65.15 | I17: (▼ $164)
B18: EV / Revenue | C18: Revenue: $40,648mm | E18: 3.2x | G18: 130074 | H18: 55.56 | I18: (▼ $173)
B19: DCF Intrinsic Value (Base Case) | H19: 229.09
B21: Note: Peer multiples based on TTM financials as of March 2026. Implied prices use PM FY2025 EBITDA/Revenue and net debt of $43,963mm.
